giftasset_sdk/__init__.py
giftasset_sdk/data.py
giftasset_sdk/dependencies.py
giftasset_sdk/giftasset_sdk.py
giftasset_sdk/rest_side.py
giftasset_sdk/modules/__init__.py
giftasset_sdk/modules/analytics.py
giftasset_sdk/modules/metadata.py
giftasset_sdk/modules/providers.py
giftasset_sdk/modules/user_data.py
giftassetsdk-0.1.3.dist-info/METADATA
giftassetsdk-0.1.3.dist-info/WHEEL
giftassetsdk-0.1.3.dist-info/top_level.txt
giftassetsdk-0.1.3.dist-info/RECORD
