Metadata-Version: 2.1
Name: giftassetsdk
Version: 0.1.3
Summary: sdk for @giftassetapi
Home-page: https://github.com/killmode696/giftasset
Author: KILLDABORNE
Author-email: dev.nevermore696@email.com
Keywords: python,library,giftassetapi,gift,asset,giftasset
Classifier: Development Status :: 3 - Alpha
Classifier: Intended Audience :: Developers
Classifier: License :: OSI Approved :: MIT License
Classifier: Programming Language :: Python :: 3
Classifier: Programming Language :: Python :: 3.7
Classifier: Programming Language :: Python :: 3.8
Classifier: Programming Language :: Python :: 3.9
Classifier: Programming Language :: Python :: 3.10
Classifier: Programming Language :: Python :: 3.11
Requires-Python: >=3.9
Requires-Dist: aiohttp==3.10.11
